{
    "@type": "Workflow",
    "triggerLimit": null,
    "name": "Setup Default Appliance Roles",
    "aliasName": null,
    "tag": null,
    "description": "Auto Configures the appliance roles for playbook execution.",
    "isActive": true,
    "debug": false,
    "singleRecordExecution": false,
    "remoteExecutableFlag": false,
    "parameters": [],
    "synchronous": false,
    "lastModifyDate": 1636537406,
    "collection": "\/api\/3\/workflow_collections\/a41c4bc4-5b29-4701-96e7-e62e21e8763e",
    "versions": [],
    "triggerStep": "\/api\/3\/workflow_steps\/7e4d4f64-5231-4b0a-b6c3-305d91a8d8f1",
    "steps": [
        {
            "@type": "WorkflowStep",
            "name": "Set Roles",
            "description": null,
            "arguments": {
                "params": {
                    "iri": "{{vars.app_id}}",
                    "body": "{   \"roles\": {{vars.role_list}}}",
                    "method": "PUT"
                },
                "version": "2.7.0",
                "connector": "cyops_utilities",
                "operation": "make_cyops_request",
                "operationTitle": "CyOPs: Make CyOPs API Call",
                "step_variables": []
            },
            "status": null,
            "top": "705",
            "left": "125",
            "stepType": "\/api\/3\/workflow_step_types\/0109f35d-090b-4a2b-bd8a-94cbc3508562",
            "uuid": "920be6e3-9a0b-4428-a081-052f24a6ba3a",
            "id": 2236
        },
        {
            "@type": "WorkflowStep",
            "name": "Make Role List",
            "description": null,
            "arguments": {
                "temp": "{% for item in vars.steps.Get_Role_IDs.data['hydra:member']%}{{vars.role_list.append(item['@id'])}}{%endfor%}"
            },
            "status": null,
            "top": "570",
            "left": "125",
            "stepType": "\/api\/3\/workflow_step_types\/04d0cf46-b6a8-42c4-8683-60a7eaa69e8f",
            "uuid": "6667b63e-c951-4418-bf9b-0f993ef549da",
            "id": 2237
        },
        {
            "@type": "WorkflowStep",
            "name": "Appliance ID",
            "description": null,
            "arguments": {
                "app_id": "{{vars.steps.Get_Appliance_ID.data[\"hydra:member\"][0][\"@id\"]}}"
            },
            "status": null,
            "top": "300",
            "left": "125",
            "stepType": "\/api\/3\/workflow_step_types\/04d0cf46-b6a8-42c4-8683-60a7eaa69e8f",
            "uuid": "9545741a-6b5b-4d22-aea6-13ca519350cd",
            "id": 2238
        },
        {
            "@type": "WorkflowStep",
            "name": "Start",
            "description": null,
            "arguments": {
                "step_variables": []
            },
            "status": null,
            "top": "30",
            "left": "125",
            "stepType": "\/api\/3\/workflow_step_types\/b348f017-9a94-471f-87f8-ce88b6a7ad62",
            "uuid": "7e4d4f64-5231-4b0a-b6c3-305d91a8d8f1",
            "id": 2239
        },
        {
            "@type": "WorkflowStep",
            "name": "Get Appliance ID",
            "description": null,
            "arguments": {
                "params": {
                    "iri": "\/api\/3\/appliances",
                    "body": "",
                    "method": "GET"
                },
                "version": "2.7.0",
                "connector": "cyops_utilities",
                "operation": "make_cyops_request",
                "operationTitle": "CyOPs: Make CyOPs API Call",
                "step_variables": []
            },
            "status": null,
            "top": "165",
            "left": "125",
            "stepType": "\/api\/3\/workflow_step_types\/0109f35d-090b-4a2b-bd8a-94cbc3508562",
            "uuid": "86cd2fca-f983-4c4a-97d8-860b3e02a6ad",
            "id": 2240
        },
        {
            "@type": "WorkflowStep",
            "name": "Get Role IDs",
            "description": null,
            "arguments": {
                "params": {
                    "iri": "\/api\/3\/roles",
                    "body": "",
                    "method": "GET"
                },
                "version": "2.7.0",
                "connector": "cyops_utilities",
                "operation": "make_cyops_request",
                "operationTitle": "CyOPs: Make CyOPs API Call",
                "step_variables": {
                    "role_list": "[]"
                }
            },
            "status": null,
            "top": "435",
            "left": "125",
            "stepType": "\/api\/3\/workflow_step_types\/0109f35d-090b-4a2b-bd8a-94cbc3508562",
            "uuid": "0ba2e92e-87ec-4172-87ad-906138f963ab",
            "id": 2241
        }
    ],
    "routes": [
        {
            "@type": "WorkflowRoute",
            "name": "Appliance ID -> Get Role IDs",
            "targetStep": "\/api\/3\/workflow_steps\/0ba2e92e-87ec-4172-87ad-906138f963ab",
            "sourceStep": "\/api\/3\/workflow_steps\/9545741a-6b5b-4d22-aea6-13ca519350cd",
            "label": null,
            "isExecuted": false,
            "uuid": "e5266035-7019-4618-a34a-2998182db93f"
        },
        {
            "@type": "WorkflowRoute",
            "name": "Make Role List -> Set Roles",
            "targetStep": "\/api\/3\/workflow_steps\/920be6e3-9a0b-4428-a081-052f24a6ba3a",
            "sourceStep": "\/api\/3\/workflow_steps\/6667b63e-c951-4418-bf9b-0f993ef549da",
            "label": null,
            "isExecuted": false,
            "uuid": "23ec3f21-6e55-43d8-828b-d9dce081ab11"
        },
        {
            "@type": "WorkflowRoute",
            "name": "Start -> Get Appliance ID",
            "targetStep": "\/api\/3\/workflow_steps\/86cd2fca-f983-4c4a-97d8-860b3e02a6ad",
            "sourceStep": "\/api\/3\/workflow_steps\/7e4d4f64-5231-4b0a-b6c3-305d91a8d8f1",
            "label": null,
            "isExecuted": false,
            "uuid": "11740025-d7f9-4d8e-8173-396852f3dc79"
        },
        {
            "@type": "WorkflowRoute",
            "name": "Get Role IDs -> Make Role List",
            "targetStep": "\/api\/3\/workflow_steps\/6667b63e-c951-4418-bf9b-0f993ef549da",
            "sourceStep": "\/api\/3\/workflow_steps\/0ba2e92e-87ec-4172-87ad-906138f963ab",
            "label": null,
            "isExecuted": false,
            "uuid": "58f05c61-dd0e-4715-bba6-7239643d0d0f"
        },
        {
            "@type": "WorkflowRoute",
            "name": "Get Appliance ID -> Appliance ID",
            "targetStep": "\/api\/3\/workflow_steps\/9545741a-6b5b-4d22-aea6-13ca519350cd",
            "sourceStep": "\/api\/3\/workflow_steps\/86cd2fca-f983-4c4a-97d8-860b3e02a6ad",
            "label": null,
            "isExecuted": false,
            "uuid": "b0fb2feb-6cb6-430d-9ebc-5d85442b358b"
        }
    ],
    "priority": null,
    "uuid": "47da90ce-6296-40ff-83f9-d87f0e0bf309",
    "recordTags": [
        "Subroutine"
    ],
    "id": 310,
    "createUser": "\/api\/3\/people\/3451141c-bac6-467c-8d72-85e0fab569ce",
    "createDate": 1636537433,
    "modifyUser": "\/api\/3\/people\/3451141c-bac6-467c-8d72-85e0fab569ce",
    "modifyDate": 1636537433,
    "owners": [],
    "isPrivate": false
}