{
    "@type": "Workflow",
    "triggerLimit": null,
    "name": "Setup Default Appliance Roles",
    "aliasName": null,
    "tag": null,
    "description": "Auto Configures the appliance roles for playbook execution.",
    "isActive": true,
    "debug": false,
    "singleRecordExecution": false,
    "remoteExecutableFlag": false,
    "parameters": [],
    "synchronous": false,
    "lastModifyDate": 1637679100,
    "collection": "\/api\/3\/workflow_collections\/a41c4bc4-5b29-4701-96e7-e62e21e8763e",
    "versions": [],
    "triggerStep": "\/api\/3\/workflow_steps\/dfc28de6-ccdc-41c8-8664-ef0fd8ec0728",
    "steps": [
        {
            "@type": "WorkflowStep",
            "name": "Set Roles",
            "description": null,
            "arguments": {
                "params": {
                    "iri": "{{vars.app_id}}",
                    "body": "{   \"roles\": {{vars.role_list}}}",
                    "method": "PUT"
                },
                "version": "2.7.0",
                "connector": "cyops_utilities",
                "operation": "make_cyops_request",
                "operationTitle": "CyOPs: Make CyOPs API Call",
                "step_variables": []
            },
            "status": null,
            "top": "705",
            "left": "125",
            "stepType": "\/api\/3\/workflow_step_types\/0109f35d-090b-4a2b-bd8a-94cbc3508562",
            "uuid": "d18941a6-6b8c-4e4c-89d6-927c1cdbff89",
            "id": 4345
        },
        {
            "@type": "WorkflowStep",
            "name": "Make Role List",
            "description": null,
            "arguments": {
                "temp": "{% for item in vars.steps.Get_Role_IDs.data['hydra:member']%}{{vars.role_list.append(item['@id'])}}{%endfor%}"
            },
            "status": null,
            "top": "570",
            "left": "125",
            "stepType": "\/api\/3\/workflow_step_types\/04d0cf46-b6a8-42c4-8683-60a7eaa69e8f",
            "uuid": "0faa7c6a-626a-4dfd-a9ab-d42d79637bdf",
            "id": 4346
        },
        {
            "@type": "WorkflowStep",
            "name": "Appliance ID",
            "description": null,
            "arguments": {
                "app_id": "{{vars.steps.Get_Appliance_ID.data[\"hydra:member\"][0][\"@id\"]}}"
            },
            "status": null,
            "top": "300",
            "left": "125",
            "stepType": "\/api\/3\/workflow_step_types\/04d0cf46-b6a8-42c4-8683-60a7eaa69e8f",
            "uuid": "a38d3af8-febb-4ed4-9418-87ff21d25144",
            "id": 4347
        },
        {
            "@type": "WorkflowStep",
            "name": "Start",
            "description": null,
            "arguments": {
                "step_variables": []
            },
            "status": null,
            "top": "30",
            "left": "125",
            "stepType": "\/api\/3\/workflow_step_types\/b348f017-9a94-471f-87f8-ce88b6a7ad62",
            "uuid": "dfc28de6-ccdc-41c8-8664-ef0fd8ec0728",
            "id": 4348
        },
        {
            "@type": "WorkflowStep",
            "name": "Get Appliance ID",
            "description": null,
            "arguments": {
                "params": {
                    "iri": "\/api\/3\/appliances",
                    "body": "",
                    "method": "GET"
                },
                "version": "2.7.0",
                "connector": "cyops_utilities",
                "operation": "make_cyops_request",
                "operationTitle": "CyOPs: Make CyOPs API Call",
                "step_variables": []
            },
            "status": null,
            "top": "165",
            "left": "125",
            "stepType": "\/api\/3\/workflow_step_types\/0109f35d-090b-4a2b-bd8a-94cbc3508562",
            "uuid": "9f1f1183-eee4-45d9-aa12-f696f523dd39",
            "id": 4349
        },
        {
            "@type": "WorkflowStep",
            "name": "Get Role IDs",
            "description": null,
            "arguments": {
                "params": {
                    "iri": "\/api\/3\/roles",
                    "body": "",
                    "method": "GET"
                },
                "version": "2.7.0",
                "connector": "cyops_utilities",
                "operation": "make_cyops_request",
                "operationTitle": "CyOPs: Make CyOPs API Call",
                "step_variables": {
                    "role_list": "[]"
                }
            },
            "status": null,
            "top": "435",
            "left": "125",
            "stepType": "\/api\/3\/workflow_step_types\/0109f35d-090b-4a2b-bd8a-94cbc3508562",
            "uuid": "ce02ead8-f492-428c-8527-bdcee38505f8",
            "id": 4350
        }
    ],
    "routes": [
        {
            "@type": "WorkflowRoute",
            "name": "Appliance ID -> Get Role IDs",
            "targetStep": "\/api\/3\/workflow_steps\/ce02ead8-f492-428c-8527-bdcee38505f8",
            "sourceStep": "\/api\/3\/workflow_steps\/a38d3af8-febb-4ed4-9418-87ff21d25144",
            "label": null,
            "isExecuted": false,
            "uuid": "4aa9a79e-c2a5-477d-a739-afcd0065127d"
        },
        {
            "@type": "WorkflowRoute",
            "name": "Make Role List -> Set Roles",
            "targetStep": "\/api\/3\/workflow_steps\/d18941a6-6b8c-4e4c-89d6-927c1cdbff89",
            "sourceStep": "\/api\/3\/workflow_steps\/0faa7c6a-626a-4dfd-a9ab-d42d79637bdf",
            "label": null,
            "isExecuted": false,
            "uuid": "cae3cd4f-da5d-4c4c-8b48-a472180b387a"
        },
        {
            "@type": "WorkflowRoute",
            "name": "Start -> Get Appliance ID",
            "targetStep": "\/api\/3\/workflow_steps\/9f1f1183-eee4-45d9-aa12-f696f523dd39",
            "sourceStep": "\/api\/3\/workflow_steps\/dfc28de6-ccdc-41c8-8664-ef0fd8ec0728",
            "label": null,
            "isExecuted": false,
            "uuid": "228ddbdf-3abb-482c-b68e-b433fd6243c0"
        },
        {
            "@type": "WorkflowRoute",
            "name": "Get Role IDs -> Make Role List",
            "targetStep": "\/api\/3\/workflow_steps\/0faa7c6a-626a-4dfd-a9ab-d42d79637bdf",
            "sourceStep": "\/api\/3\/workflow_steps\/ce02ead8-f492-428c-8527-bdcee38505f8",
            "label": null,
            "isExecuted": false,
            "uuid": "e6a1f53a-31d1-450e-949d-c67ebaf3a9bb"
        },
        {
            "@type": "WorkflowRoute",
            "name": "Get Appliance ID -> Appliance ID",
            "targetStep": "\/api\/3\/workflow_steps\/a38d3af8-febb-4ed4-9418-87ff21d25144",
            "sourceStep": "\/api\/3\/workflow_steps\/9f1f1183-eee4-45d9-aa12-f696f523dd39",
            "label": null,
            "isExecuted": false,
            "uuid": "6d92901a-d3b8-4eb7-b07b-fdb1f12aa630"
        }
    ],
    "priority": null,
    "uuid": "47da90ce-6296-40ff-83f9-d87f0e0bf309",
    "recordTags": [
        "Subroutine"
    ],
    "id": 1138,
    "createUser": "\/api\/3\/appliances\/57545210-2adc-472b-a24f-2df6ee8dfe63",
    "createDate": 1637679116,
    "modifyUser": "\/api\/3\/appliances\/57545210-2adc-472b-a24f-2df6ee8dfe63",
    "modifyDate": 1637679116,
    "owners": [],
    "isPrivate": false
}